Metadata-Version: 2.1
Name: odoo12-addon-l10n-es-partner
Version: 12.0.1.0.4
Summary: Adaptación de los clientes, proveedores y bancos para España
Home-page: https://github.com/OCA/l10n-spain
Author: ZikZak,Acysos,Tecnativa,Odoo Community Association (OCA)
Author-email: support@odoo-community.org
License: AGPL-3
Platform: UNKNOWN
Classifier: Programming Language :: Python
Classifier: Framework :: Odoo
Classifier: Framework :: Odoo :: 12.0
Classifier: License :: OSI Approved :: GNU Affero General Public License v3
Classifier: Development Status :: 6 - Mature
Requires-Python: >=3.5
Requires-Dist: odoo12-addon-base-bank-from-iban
Requires-Dist: odoo <12.1dev,>=12.0a
Requires-Dist: requests
